lgbm2vhdl/Common.py
lgbm2vhdl/GenVHDLCommon.py
lgbm2vhdl/GenVHDLMemC.py
lgbm2vhdl/GenVHDLMemC_Mem.py
lgbm2vhdl/GenVHDLMemC_Ord.py
lgbm2vhdl/GenVHDLMemC_Ord_Mem.py
lgbm2vhdl/GenVHDLTestbench.py
lgbm2vhdl/GenVHDLWrapper.py
lgbm2vhdl/LGBM2VHDL.py
lgbm2vhdl/LGBModel.py
lgbm2vhdl/LGBTree.py
lgbm2vhdl/RunSimulation.py
lgbm2vhdl/TemplateFile.py
lgbm2vhdl/__init__.py
lgbm2vhdl/template/build/Makefile.amd
lgbm2vhdl/template/build/Makefile.intel
lgbm2vhdl/template/build/design.amd.tcl
lgbm2vhdl/template/build/design.intel.tcl
lgbm2vhdl/template/build/design.sdc
lgbm2vhdl/template/build/design.xdc
lgbm2vhdl/template/cmp_ord/cmp_ord_fsm_group_mt.vhd
lgbm2vhdl/template/cmp_ord/cmp_ord_group_mt.vhd
lgbm2vhdl/template/cmp_ord/cmp_ord_group_mt_core.vhd
lgbm2vhdl/template/common/barrier.vhd
lgbm2vhdl/template/common/cnt_fsm.vhd
lgbm2vhdl/template/common/dp_ram.vhd
lgbm2vhdl/template/common/dtype_pkg.vhd
lgbm2vhdl/template/common/rom.vhd
lgbm2vhdl/template/mem-c/mem-c_mux.vhd
lgbm2vhdl/template/mem-c/mem-c_pe_fsm.vhd
lgbm2vhdl/template/mem-c/mem-c_pe_fsm_mt.vhd
lgbm2vhdl/template/mem-c/mem-c_pe_mt.vhd
lgbm2vhdl/template/mem-c/mem-c_pe_mt_mem.vhd
lgbm2vhdl/template/mem-c/mem-c_top.vhd
lgbm2vhdl/template/mem-c_mem/mem-c_mem_top.vhd
lgbm2vhdl/template/mem-c_ord/dtype_memc_ord_pkg.vhd
lgbm2vhdl/template/mem-c_ord/mem-c_ord_barrier.vhd
lgbm2vhdl/template/mem-c_ord/mem-c_ord_top.vhd
lgbm2vhdl/template/mem-c_ord_mem/mem-c_ord_mem_mem_pe.vhd
lgbm2vhdl/template/mem-c_ord_mem/mem-c_ord_mem_mem_pe_single.vhd
lgbm2vhdl/template/mem-c_ord_mem/mem-c_ord_mem_top.vhd
lgbm2vhdl/template/sim/testbench.vhd
lgbm2vhdl/template/sim/vcom.do
lgbm2vhdl/template/sim/vsim.do
lgbm2vhdl/template/sim/wave.do
lgbm2vhdl/template/wrapper/wrapper.vhd
lgbm2vhdl/template/wrapper/wrapper_mem.vhd
lgbm2vhdl-0.0.2.dist-info/METADATA
lgbm2vhdl-0.0.2.dist-info/WHEEL
lgbm2vhdl-0.0.2.dist-info/entry_points.txt
lgbm2vhdl-0.0.2.dist-info/license_files/LICENSE
lgbm2vhdl-0.0.2.dist-info/RECORD
