Metadata-Version: 2.1
Name: lgbm2vhdl
Version: 0.0.2
Summary: Translation of LightGBM model to VHDL
Project-URL: Bug Tracker, https://github.com/CESNET/lgbm2vhdl/issues
Project-URL: Homepage, https://github.com/CESNET/lgbm2vhdl
Author-email: Tomas Martinek <martinek@cesnet.cz>
Keywords: LightGBM,VHDL,machine learning,traffic classification
Classifier: License :: OSI Approved :: BSD License
Classifier: Operating System :: OS Independent
Classifier: Programming Language :: Python :: 3
Requires-Python: >=3.9
Requires-Dist: fxpmath
Requires-Dist: lightgbm
Requires-Dist: numpy
Requires-Dist: pandas
